simple_file_handler/__init__.py
simple_file_handler/exceptions.py
simple_file_handler/handler.py
simple_file_handler-0.0.1.dist-info/LICENSE
simple_file_handler-0.0.1.dist-info/METADATA
simple_file_handler-0.0.1.dist-info/WHEEL
simple_file_handler-0.0.1.dist-info/top_level.txt
simple_file_handler-0.0.1.dist-info/RECORD
