Metadata-Version: 2.1
Name: simple_file_handler
Version: 0.0.1
Summary: An easy to use interface for basic file handling operations.
Author-email: ti-oluwa <tioluwa.dev@gmail.com>
Maintainer-email: ti-oluwa <tioluwa.dev@gmail.com>
Project-URL: Homepage, https://github.com/ti-oluwa/simple_file_handler
Project-URL: Bug Tracker, https://github.com/ti-oluwa/simple_file_handler/issues
Project-URL: Repository, https://github.com/ti-oluwa/simple_file_handler
Keywords: file,file-handling,file-handler,file-handlers,file-handling-operations,file-handling-operation,write-to-file,read-from-file,copy-file,move-file,delete-file
Classifier: Programming Language :: Python :: 3
Classifier: License :: OSI Approved :: GNU General Public License v3 (GPLv3)
Classifier: Operating System :: OS Independent
Classifier: Development Status :: 4 - Beta
Classifier: Intended Audience :: Developers
Classifier: Topic :: Software Development :: Libraries :: Python Modules
Classifier: Topic :: Utilities
Classifier: Natural Language :: English
Classifier: Typing :: Typed
Requires-Python: >=3.7
License-File: LICENSE
Requires-Dist: toml
Requires-Dist: pyyaml
